skill_translation/LICENSE.md
skill_translation/README.md
skill_translation/__init__.py
skill_translation/skill.json
skill_translation/version.py
skill_translation/locale/en-us/languages.value
skill_translation/locale/en-us/dialog/language_not_supported.dialog
skill_translation/locale/en-us/dialog/phrase_in_language.dialog
skill_translation/locale/en-us/vocab/female.voc
skill_translation/locale/en-us/vocab/male.voc
skill_translation/locale/en-us/vocab/translate_phrase.intent
skill_translation/neon_skill_translation.egg-info/PKG-INFO
skill_translation/neon_skill_translation.egg-info/SOURCES.txt
skill_translation/neon_skill_translation.egg-info/dependency_links.txt
skill_translation/neon_skill_translation.egg-info/entry_points.txt
skill_translation/neon_skill_translation.egg-info/requires.txt
skill_translation/neon_skill_translation.egg-info/top_level.txt
skill_translation/test/test_skill.py
skill_translation/ui/Translation.qml
skill_translation/ui/qmldir
neon_skill_translation-1.0.2.dist-info/LICENSE.md
neon_skill_translation-1.0.2.dist-info/METADATA
neon_skill_translation-1.0.2.dist-info/WHEEL
neon_skill_translation-1.0.2.dist-info/entry_points.txt
neon_skill_translation-1.0.2.dist-info/top_level.txt
neon_skill_translation-1.0.2.dist-info/RECORD
